mcp_wireshark/__init__.py
mcp_wireshark/cli.py
mcp_wireshark/py.typed
mcp_wireshark/server.py
mcp_wireshark/types.py
mcp_wireshark/utils.py
mcp_wireshark-0.1.1.dist-info/licenses/LICENSE
mcp_wireshark-0.1.1.dist-info/METADATA
mcp_wireshark-0.1.1.dist-info/WHEEL
mcp_wireshark-0.1.1.dist-info/entry_points.txt
mcp_wireshark-0.1.1.dist-info/top_level.txt
mcp_wireshark-0.1.1.dist-info/RECORD
