Metadata-Version: 2.4
Name: mcp-wireshark
Version: 0.1.1
Summary: [Unofficial/Community] MCP server for Wireshark/tshark integration with AI tools
Author: Khang Nguyen Huynh
License: MIT
Project-URL: Homepage, https://github.com/khuynh22/mcp-wireshark
Project-URL: Repository, https://github.com/khuynh22/mcp-wireshark
Project-URL: Issues, https://github.com/khuynh22/mcp-wireshark/issues
Project-URL: Documentation, https://github.com/khuynh22/mcp-wireshark#readme
Project-URL: Changelog, https://github.com/khuynh22/mcp-wireshark/blob/main/CHANGELOG.md
Keywords: mcp,model-context-protocol,wireshark,tshark,network-analysis,packet-capture,pcap,ai-tools,claude,llm
Classifier: Development Status :: 4 - Beta
Classifier: Intended Audience :: Developers
Classifier: Intended Audience :: Information Technology
Classifier: Intended Audience :: System Administrators
Classifier: License :: OSI Approved :: MIT License
Classifier: Programming Language :: Python :: 3
Classifier: Programming Language :: Python :: 3.10
Classifier: Programming Language :: Python :: 3.11
Classifier: Programming Language :: Python :: 3.12
Classifier: Programming Language :: Python :: 3.13
Classifier: Operating System :: OS Independent
Classifier: Topic :: Software Development :: Libraries :: Python Modules
Classifier: Topic :: System :: Networking :: Monitoring
Classifier: Topic :: Security
Classifier: Typing :: Typed
Requires-Python: >=3.10
License-File: LICENSE
Requires-Dist: mcp>=0.9.0
Requires-Dist: pyshark>=0.6
Requires-Dist: typing-extensions>=4.0.0
Provides-Extra: dev
Requires-Dist: pytest>=7.0; extra == "dev"
Requires-Dist: pytest-asyncio>=0.21.0; extra == "dev"
Requires-Dist: pytest-cov>=4.0; extra == "dev"
Requires-Dist: mypy>=1.0; extra == "dev"
Requires-Dist: black>=23.0; extra == "dev"
Requires-Dist: ruff>=0.1.0; extra == "dev"
Requires-Dist: pre-commit>=3.0; extra == "dev"
Provides-Extra: docs
Requires-Dist: mkdocs>=1.5; extra == "docs"
Requires-Dist: mkdocs-material>=9.0; extra == "docs"
Requires-Dist: mkdocstrings[python]>=0.24; extra == "docs"
Dynamic: license-file
